wetest/pyidb/__init__.py
wetest/pyidb/_log.py
wetest/pyidb/_protocols.py
wetest/pyidb/_utils.py
wetest/pyidb/exceptions.py
wetest/pyidb/idb.py
wetest_pyidb-0.0.5.dist-info/METADATA
wetest_pyidb-0.0.5.dist-info/WHEEL
wetest_pyidb-0.0.5.dist-info/top_level.txt
wetest_pyidb-0.0.5.dist-info/RECORD
