Metadata-Version: 2.4
Name: wetest-pyidb
Version: 0.0.5
Author: Tencent WeTest
Author-email: WeTest@wetest.net
Requires-Python: >=3.8
Requires-Dist: packaging
Requires-Dist: requests
Requires-Dist: pydantic
Requires-Dist: wetest-osplatform
Dynamic: author
Dynamic: author-email
Dynamic: description
Dynamic: description-content-type
Dynamic: requires-dist
Dynamic: requires-python
